bqplot/__init__.py
bqplot/_version.py
bqplot/axes.py
bqplot/colorschemes.py
bqplot/default_tooltip.py
bqplot/figure.py
bqplot/install.py
bqplot/interacts.py
bqplot/market_map.py
bqplot/marks.py
bqplot/plotting_widgets.py
bqplot/pyplot.py
bqplot/scales.py
bqplot/toolbar.py
bqplot/traits.py
bqplot/map_data/EuropeMap.json
bqplot/map_data/USCountiesMap.json
bqplot/map_data/USStatesMap.json
bqplot/map_data/WorldMap.json
bqplot-0.12.43.data/data/etc/jupyter/nbconfig/notebook.d/bqplot.json
bqplot-0.12.43.data/data/share/jupyter/labextensions/bqplot/install.json
bqplot-0.12.43.data/data/share/jupyter/labextensions/bqplot/package.json
bqplot-0.12.43.data/data/share/jupyter/labextensions/bqplot/static/133.184b7ff4eeea6053c218.js
bqplot-0.12.43.data/data/share/jupyter/labextensions/bqplot/static/212.898d3b3da016aa77edc1.js
bqplot-0.12.43.data/data/share/jupyter/labextensions/bqplot/static/212.898d3b3da016aa77edc1.js.LICENSE.txt
bqplot-0.12.43.data/data/share/jupyter/labextensions/bqplot/static/501.6c13f92ce49688bde790.js
bqplot-0.12.43.data/data/share/jupyter/labextensions/bqplot/static/568.d098e2e89d2e163b9080.js
bqplot-0.12.43.data/data/share/jupyter/labextensions/bqplot/static/662.d928d9e888427c5996be.js
bqplot-0.12.43.data/data/share/jupyter/labextensions/bqplot/static/794.8d6261fd8a7307e156f7.js
bqplot-0.12.43.data/data/share/jupyter/labextensions/bqplot/static/815.4fcd9a1489787115f930.js
bqplot-0.12.43.data/data/share/jupyter/labextensions/bqplot/static/842.a94bbf6f3349e982fb8b.js
bqplot-0.12.43.data/data/share/jupyter/labextensions/bqplot/static/87.cc5d175e0ffc0d125bd5.js
bqplot-0.12.43.data/data/share/jupyter/labextensions/bqplot/static/981.3f93685e278b785a3338.js
bqplot-0.12.43.data/data/share/jupyter/labextensions/bqplot/static/981.3f93685e278b785a3338.js.LICENSE.txt
bqplot-0.12.43.data/data/share/jupyter/labextensions/bqplot/static/remoteEntry.a36d13f475360b3d8988.js
bqplot-0.12.43.data/data/share/jupyter/labextensions/bqplot/static/style.js
bqplot-0.12.43.dist-info/LICENSE
bqplot-0.12.43.dist-info/METADATA
bqplot-0.12.43.dist-info/WHEEL
bqplot-0.12.43.dist-info/top_level.txt
bqplot-0.12.43.dist-info/RECORD
