Metadata-Version: 2.1
Name: bqplot
Version: 0.12.43
Summary: Interactive plotting for the Jupyter notebook, using d3.js and ipywidgets.
Home-page: https://github.com/bqplot/bqplot
Author: The BQplot Development Team
License: Apache
Keywords: ipython,jupyter,widgets,graphics,plotting,d3
Requires-Python: >=3.6
License-File: LICENSE
Requires-Dist: ipywidgets<9,>=7.5.0
Requires-Dist: traitlets>=4.3.0
Requires-Dist: traittypes>=0.0.6
Requires-Dist: numpy>=1.10.4
Requires-Dist: pandas<3.0.0,>=1.0.0
